<annotation><folder>4--Dancing</folder><filename>4_Dancing_Dancing_4_120.jpg</filename><path>./WIDER_train/images/4--Dancing/4_Dancing_Dancing_4_120.jpg</path><source><database>Unknown</database></source><size><width>1024</width><height>1114</height><depth>3</depth></size><segmented>0</segmented><object><name>face</name><pose>Unspecified</pose><truncated>0</truncated><difficult>0</difficult><bndbox><xmin>245</xmin><ymin>114</ymin><xmax>300</xmax><ymax>195</ymax></bndbox></object><object><name>face</name><pose>Unspecified</pose><truncated>0</truncated><difficult>0</difficult><bndbox><xmin>339</xmin><ymin>180</ymin><xmax>375</xmax><ymax>236</ymax></bndbox></object><object><name>face</name><pose>Unspecified</pose><truncated>0</truncated><difficult>0</difficult><bndbox><xmin>151</xmin><ymin>230</ymin><xmax>188</xmax><ymax>284</ymax></bndbox></object><object><name>face</name><pose>Unspecified</pose><truncated>0</truncated><difficult>0</difficult><bndbox><xmin>536</xmin><ymin>150</ymin><xmax>641</xmax><ymax>289</ymax></bndbox></object><object><name>face</name><pose>Unspecified</pose><truncated>0</truncated><difficult>0</difficult><bndbox><xmin>642</xmin><ymin>236</ymin><xmax>671</xmax><ymax>277</ymax></bndbox></object></annotation>