<annotation><folder>52--Photographers</folder><filename>52_Photographers_taketouristphotos_52_687.jpg</filename><path>./WIDER_train/images/52--Photographers/52_Photographers_taketouristphotos_52_687.jpg</path><source><database>Unknown</database></source><size><width>1024</width><height>766</height><depth>3</depth></size><segmented>0</segmented><object><name>face</name><pose>Unspecified</pose><truncated>0</truncated><difficult>0</difficult><bndbox><xmin>474</xmin><ymin>282</ymin><xmax>502</xmax><ymax>319</ymax></bndbox></object><object><name>face</name><pose>Unspecified</pose><truncated>0</truncated><difficult>0</difficult><bndbox><xmin>507</xmin><ymin>439</ymin><xmax>530</xmax><ymax>470</ymax></bndbox></object><object><name>face</name><pose>Unspecified</pose><truncated>0</truncated><difficult>0</difficult><bndbox><xmin>475</xmin><ymin>446</ymin><xmax>497</xmax><ymax>471</ymax></bndbox></object></annotation>